[
  {
    "id": "nameID",
    "name": "name",
    "type": "text",
    "placeholder": "Ime",
    "required": true,
    "className": "md:col-span-1"
  },
  {
    "id": "emailID",
    "name": "email",
    "type": "email",
    "placeholder": "Email",
    "required": true,
    "className": "md:col-span-1"
  },
  {
    "id": "messageID",
    "name": "message",
    "type": "textarea",
    "placeholder": "Komentar",
    "required": true
  },
  {
    "id": "comment_is_anonymousID",
    "name": "is_anonymous",
    "type": "checkbox",
    "placeholder": "Želim da budem anoniman",
    "required": false,
    "className": "col-span-full"
  },
  {
    "id": "comment_imageID",
    "name": "comment_images",
    "type": "file",
    "placeholder": "Postavi sliku",
    "required": false,
    "className": "md:col-span-1"
  },
  {
    "id": "comment_videoID",
    "name": "comment_videos",
    "type": "file",
    "placeholder": "Postavi video",
    "required": false,
    "className": "md:col-span-1"
  }
]
